Workbook

Sheet Read Me
B2: SMART START — Student Management Workbook
B3: Attendance • Student Records • Per-Class Fees
B6: HOW THE COLOURS WORK
B7: Yellow cells | C7: You type in these — the only cells you edit.
B8: White / grey cells | C8: Calculated automatically. Leave them alone; they update on their own.
B10: HOW FEES WORK (per class)
B11: Rate by grade | C11: Fees are charged per class attended. Rate depends on grade: JK & SK = $10, Grade 1-4 = $15, Grade 5-8 = $20. These live in the Fee Structure sheet.
B12: Automatic billing | C12: Set each child's Grade in the Students sheet. Their per-class rate fills in automatically. The Fees sheet then multiplies classes attended (from Attendance) by that rate to get the amount due.
B14: THE SHEETS
B15: Students | C15: Master list: name, parents, contact, address, grade, subjects, per-class rate (auto), status. Source of truth — set each child's Grade here.
B16: Fee Structure | C16: The per-class price list by grade. Formulas read the rate from here — edit the numbers if your pricing changes.
B17: Attendance Aug 2026 | C17: Mark P (present) or A (absent) per child per class day. Present count feeds the fee calculation.
B18: Fees Aug 2026 | C18: Amount due = classes attended x per-class rate (both filled automatically). Type the Amount Paid; Balance and Status calculate themselves.
B19: Payments Log | C19: A running receipt book — one line per payment received.
B20: Dashboard | C20: Live totals: active students, fees billed / collected / outstanding, average attendance.
B22: MAKING A NEW MONTH
B23: Duplicate the tab | C23: Right-click 'Attendance Aug 2026' (or 'Fees Aug 2026') → Duplicate → rename to the new month. Formulas copy across.
B25: BILLING ASSUMPTION
B26: Charged on classes held | C26: A child is billed for every class held (present + absent) — absences are still charged. Only days left blank (no class) are free. Want to bill on attendance instead? Just ask.
B28: YOUR EXISTING DATA
B29: Carried over | C29: Roster: Fateh, Amolpreet, Ravjot, Alaina. Prior Aug totals (old sheet, ~Aug 11): Fateh 5 · Amolpreet 6 · Ravjot 2 · Alaina 0 classes. Daily marks were inconsistent across your old tabs, so the grid is blank to fill going forward. Set each child's Grade so their rate and fees calculate.

Sheet Fee Structure
A1: Grade | B1: Per-Class Rate ($) | C1: Notes
A2: JK | B2: 10 | C2: Junior Kindergarten
A3: SK | B3: 10 | C3: Senior Kindergarten
A4: Grade 1 | B4: 15
A5: Grade 2 | B5: 15
A6: Grade 3 | B6: 15
A7: Grade 4 | B7: 15
A8: Grade 5 | B8: 20
A9: Grade 6 | B9: 20
A10: Coding | B10: 25
A11: Grade 7 | B11: 20
A12: Grade 8 | B12: 20
A13: Rates are per class attended. Edit the yellow rate cells if pricing changes.

Sheet Schedule
A1: CLASS SCHEDULE
A2: The timetable that feeds Google Calendar. Fill the config + rows below, then run the sync script (see setup guide).
A4: Term Start | B4: 2026-09-02 | C4: ← first day classes run
A5: Term End | B5: 2026-12-19 | C5: ← last day classes run
A6: Calendar Name | B6: Smart Start Classes | C6: ← the calendar events go into
A8: Group / Class | B8: Day | C8: Start (HH:MM) | D8: End (HH:MM) | E8: Subject | F8: Location | G8: Teacher | H8: Parent Emails (comma-separated) | I8: Notes
A9: (Example) Grade 1-4 Core | B9: Wed | C9: 23:20 | D9: 23:30 | E9: Math & English | F9: Caledon Centre | G9: Tarun | H9: messielectra@gmail.com | I9: Weekly
A10: (Example) Grade 1-4 Core | B10: Thu | C10: 17:00 | D10: 18:00 | E10: Math & English | F10: Caledon Centre | G10: Tarun | H10: parent1@email.com, parent2@email.com | I10: Weekly
A11: (Example) Grade 5-8 Core | B11: Sat | C11: 10:00 | D11: 11:30 | E11: Math/Eng/Sci | F11: Caledon Centre | G11: Tarun | H11: parent3@email.com | I11: Weekly
A28: Times are 24-hour text, e.g. 17:00. Delete the green example rows before syncing. Parent Emails get calendar invites.

Sheet Students
A1: Student ID | B1: Full Name | C1: Date of Birth | D1: Grade / Level | E1: School | F1: Subjects Enrolled | G1: Address | H1: Parent / Guardian Name | I1: Primary Contact | J1: Alternate Contact | K1: Email | L1: Emergency Contact Name | M1: Emergency Contact Phone | N1: Enrollment Date | O1: Per-Class Rate ($) | P1: Status | Q1: Notes
A2: SS000 | B2: (Example) Priya Sharma | C2: 2015-04-12 | D2: Grade 4 | E2: Maple Ridge PS | F2: Math, English | G2: 12 King St, Caledon, ON | H2: Anita Sharma | I2: 416-555-0100 | J2: 647-555-0100 | K2: anita@email.com | L2: Rohit Sharma | M2: 416-555-0199 | N2: 2026-01-15 | O2: {=IFERROR(INDEX('Fee Structure'!$B$2:$B$12,MATCH($D2,'Fee Structure'!$A$2:$A$12,0)),"")} -> 15 | P2: Example | Q2: ← EXAMPLE ROW — delete before use
A3: SS001 | B3: Fateh | D3: Grade 7 | E3: Tony Pontes Public School | F3: All | G3: 62 Blackberry valley Crescent, Caledon, ON | H3: Jasbir | I3: 416-893-0898 | J3: Batch1 | O3: {=IFERROR(INDEX('Fee Structure'!$B$2:$B$12,MATCH($D3,'Fee Structure'!$A$2:$A$12,0)),"")} -> 20 | P3: Active
A4: SS002 | B4: Ravjodh | D4: Grade 2 | E4: Tony Pontes Public School | F4: All | G4: 158 Newhouse Boulevard | H4: Maninder | I4: 647-201-6812 | J4: Batch3 | O4: {=IFERROR(INDEX('Fee Structure'!$B$2:$B$12,MATCH($D4,'Fee Structure'!$A$2:$A$12,0)),"")} -> 15 | P4: Active
A5: SS003 | B5: Alaina | C5: 41920 | D5: Grade 7 | E5: Tony Pontes Public School | F5: All | G5: 156 Newhouse boulevard | H5: Priya Tandon | I5: 226-886-4462 | J5: Batch1 | O5: {=IFERROR(INDEX('Fee Structure'!$B$2:$B$12,MATCH($D5,'Fee Structure'!$A$2:$A$12,0)),"")} -> 20 | P5: Active | Q5: Want to pair the same day as Ravjodh
A6: SS004 | B6: Kaya | D6: Grade 3 | E6: Tony Pontes Public School | F6: All | H6: Bina | I6: 647-708-8550 | J6: Batch3 | O6: {=IFERROR(INDEX('Fee Structure'!$B$2:$B$12,MATCH($D6,'Fee Structure'!$A$2:$A$12,0)),"")} -> 15 | P6: Active
A7: SS005 | B7: Gurshabd Singh Rawala | C7: 44284 | D7: SK | E7: Tony Pontes Public School | F7: All | G7: 48 Blackberry Valley Crescent Caledon | H7: Ashwinder | I7: 647-939-6794 437-430-6111 | J7: Batch2 | O7: {=IFERROR(INDEX('Fee Structure'!$B$2:$B$12,MATCH($D7,'Fee Structure'!$A$2:$A$12,0)),"")} -> 10 | P7: Active
A8: SS006 | B8: Baani Purba | C8: 44767 | D8: Grade 3 | E8: James Grieve Public School | F8: All | G8: 27 Valleyscape Trail, Caledon | H8: Gagandeep Purba | I8: 647-260-6420 647-648-5718 | J8: Batch3 | O8: {=IFERROR(INDEX('Fee Structure'!$B$2:$B$12,MATCH($D8,'Fee Structure'!$A$2:$A$12,0)),"")} -> 15 | P8: Active | Q8: Planned from sept 8
A9: SS007 | B9: Avneet Kaur Grewal | C9: 42567 | D9: Grade 5 | E9: James Grieve Public School | F9: All | G9: 25 Valleyscape Trail, Caledon | H9: Jagdip Singh Grewal | I9: 416-844-6548 647-389-6783 | J9: Batch3 | O9: {=IFERROR(INDEX('Fee Structure'!$B$2:$B$12,MATCH($D9,'Fee Structure'!$A$2:$A$12,0)),"")} -> 20 | P9: Active
A10: SS008 | B10: Tanisha | D10: Coding | E10: Mayfield secondary school | F10: Coding | H10: Ruchi | J10: Batch4 | O10: {=IFERROR(INDEX('Fee Structure'!$B$2:$B$12,MATCH($D10,'Fee Structure'!$A$2:$A$12,0)),"")} -> 25 | P10: Active
A11: SS009 | B11: xyz | D11: Grade 2 | E11: Somerset Public school | F11: All | H11: Sharn | O11: {=IFERROR(INDEX('Fee Structure'!$B$2:$B$12,MATCH($D11,'Fee Structure'!$A$2:$A$12,0)),"")} -> 15 | P11: Inquiry
A12: SS010 | B12: Ekamjot | D12: Coding | E12: Mayfield secondary school | F12: Coding | H12: Jasbir | J12: Batch4 | O12: {=IFERROR(INDEX('Fee Structure'!$B$2:$B$12,MATCH($D12,'Fee Structure'!$A$2:$A$12,0)),"")} -> 25 | P12: Inactive
A13: SS011 | B13: Viraj | D13: Coding | E13: Mayfield secondary school | F13: Coding | H13: Sonia | J13: Batch4 | O13: {=IFERROR(INDEX('Fee Structure'!$B$2:$B$12,MATCH($D13,'Fee Structure'!$A$2:$A$12,0)),"")} -> 25 | P13: Inactive
A14: SS012 | B14: Amolpreet | D14: SK | E14: Tony Pontes Public School | F14: All | G14: 560 Dougall Avenue, Caledon | H14: Khushi | I14: 437-979-7072 | J14: Batch2 | O14: {=IFERROR(INDEX('Fee Structure'!$B$2:$B$12,MATCH($D14,'Fee Structure'!$A$2:$A$12,0)),"")} -> 10 | P14: Inactive
A15: SS013 | B15: Ekjot | D15: Grade 1 | E15: Tony Pontes Public School | F15: All | H15: Aman | I15: 647-473-2683 | O15: {=IFERROR(INDEX('Fee Structure'!$B$2:$B$12,MATCH($D15,'Fee Structure'!$A$2:$A$12,0)),"")} -> 15 | P15: Inactive | Q15: Want classes on weekend atleast1
A16: SS014 | B16: Aarna | D16: JK | E16: Tony Pontes Public School | F16: All | H16: Gopinath | I16: 289-207-2439 | O16: {=IFERROR(INDEX('Fee Structure'!$B$2:$B$12,MATCH($D16,'Fee Structure'!$A$2:$A$12,0)),"")} -> 10 | P16: Inactive
A17: SS015 | D17: SK | H17: Riddhi | I17: 437-688-3621 | O17: {=IFERROR(INDEX('Fee Structure'!$B$2:$B$12,MATCH($D17,'Fee Structure'!$A$2:$A$12,0)),"")} -> 10 | P17: Inactive
A18: SS016 | D18: Grade 1 | H18: Mahesh Patel | I18: 437-376-2743 | O18: {=IFERROR(INDEX('Fee Structure'!$B$2:$B$12,MATCH($D18,'Fee Structure'!$A$2:$A$12,0)),"")} -> 15 | P18: Inactive | Q18: Need ceritified teacher
A19: SS017 | O19: {=IFERROR(INDEX('Fee Structure'!$B$2:$B$12,MATCH($D19,'Fee Structure'!$A$2:$A$12,0)),"")} | P19: Inquiry
A20: SS018 | O20: {=IFERROR(INDEX('Fee Structure'!$B$2:$B$12,MATCH($D20,'Fee Structure'!$A$2:$A$12,0)),"")}
A21: SS018
A22: SS017

Sheet Attendance Aug 2026
A1: ATTENDANCE — AUGUST 2026
A2: Mark P = Present · A = Absent · blank if no class. Totals calculate automatically.
C3: S | D3: S | E3: M | F3: T | G3: W | H3: T | I3: F | J3: S | K3: S | L3: M | M3: T | N3: W | O3: T | P3: F | Q3: S | R3: S | S3: M | T3: T | U3: W | V3: T | W3: F | X3: S | Y3: S | Z3: M | AA3: T | AB3: W | AC3: T | AD3: F | AE3: S | AF3: S | AG3: M
A4: Student ID | B4: Name | C4: 1 | D4: 2 | E4: 3 | F4: 4 | G4: 5 | H4: 6 | I4: 7 | J4: 8 | K4: 9 | L4: 10 | M4: 11 | N4: 12 | O4: 13 | P4: 14 | Q4: 15 | R4: 16 | S4: 17 | T4: 18 | U4: 19 | V4: 20 | W4: 21 | X4: 22 | Y4: 23 | Z4: 24 | AA4: 25 | AB4: 26 | AC4: 27 | AD4: 28 | AE4: 29 | AF4: 30 | AG4: 31 | AH4: Total Classes Scheduled | AI4: Present | AJ4: Absent | AK4: Classes Held | AL4: Attendance % | AM4: Batches
A5: SS001 | B5: Fateh | D5: P | E5: P | G5: P | I5: P | L5: P | N5: A | P5: P | S5: A | U5: P | V5: P | Z5: P | AB5: P | AG5: P | AH5: 13 | AI5: 11 | AJ5: 2 | AK5: 13 | AL5: 0.84615385 | AM5: Batch1
A6: SS002 | B6: Amolpreet | D6: P | F6: P | H6: P | J6: P | K6: P | M6: P | O6: P | P6: P | S6: P | T6: P | U6: P | V6: P | Z6: P | AA6: A | AC6: P | AG6: A | AH6: 16 | AI6: 14 | AJ6: 2 | AK6: 16 | AL6: 0.875 | AM6: Batch2
A7: SS003 | B7: Ravjodh | L7: P | M7: P | O7: P | P7: P | S7: A | T7: P | U7: P | V7: P | Z7: P | AA7: P | AC7: P | AG7: P | AH7: 12 | AI7: 11 | AJ7: 1 | AK7: 12 | AL7: 0.91666667 | AM7: Batch2
A8: SS004 | B8: Alaina | N8: P | P8: P | S8: P | U8: P | V8: P | Z8: P | AB8: P | AG8: P | AH8: 8 | AI8: 8 | AJ8: 0 | AK8: 8 | AL8: 1 | AM8: Batch1
A9: SS005 | B9: Kaya | O9: P | S9: A | V9: P | Z9: P | AC9: P | AG9: P | AH9: 6 | AI9: 5 | AJ9: 1 | AK9: 6 | AL9: 0.83333333 | AM9: Batch2
A10: SS006 | B10: Gurshabd | S10: P | T10: P | U10: P | V10: P | Z10: P | AA10: P | AC10: P | AG10: P | AH10: 8 | AI10: 8 | AJ10: 0 | AK10: 8 | AL10: 1 | AM10: Batch2
A11: Prior Aug totals (old sheet, ~Aug 11): Fateh 5 · Amolpreet 6 · Ravjot 2 · Alaina 0. Backfill days 1-11 for an exact record.

Sheet Fees Aug 2026
A1: FEES — AUGUST 2026 (per class attended)
A2: Amount Due = classes held x per-class rate (absences still billed). Type Amount Paid; Balance & Status calculate.
A4: Student ID | B4: Name | C4: Grade | D4: Rate ($/class) | E4: Classes Held (billed) | F4: Classes Scheduled | G4: Amount Due ($) | H4: Amount Paid ($) | I4: Balance ($) | J4: Status | K4: Payment Date | L4: Method | M4: Notes
A5: SS001 | B5: Fateh | C5: Grade 7 | D5: 20 | E5: 13 | F5: 13 | G5: 260 | H5: 260 | I5: 0 | J5: Paid | K5: 46262 | L5: Cash | M5: Batch1
A6: SS002 | B6: Amolpreet | C6: SK | D6: 10 | E6: 16 | F6: 16 | G6: 160 | H6: 160 | I6: 0 | J6: Paid | K6: 46236 | L6: Cash | M6: Batch2
A7: SS003 | B7: Ravjodh | C7: Grade 2 | D7: 15 | E7: 12 | F7: 12 | G7: 180 | H7: 180 | I7: 0 | J7: Paid | K7: 42600 | L7: Cash | M7: Batch2
A8: SS004 | B8: Alaina | C8: Grade 7 | D8: 20 | E8: 8 | F8: 8 | G8: 160 | H8: 160 | I8: 0 | J8: Paid | K8: 46251 | L8: Cash | M8: Batch1
A9: SS005 | B9: Kaya | C9: Grade 3 | D9: 15 | E9: 6 | F9: 6 | G9: 90 | H9: 100 | I9: -10 | J9: Paid | K9: 46254 | L9: Cash | M9: Batch2
A10: SS006 | B10: Gurshabd | C10: SK | D10: 10 | E10: 8 | F10: 8 | G10: 80 | H10: 100 | I10: -20 | J10: Paid | K10: 46265 | L10: Cash | M10: Batch2
B11: TOTAL | G11: 930 | H11: 960 | I11: -30
C20: .

Sheet Report Aug 2026
A1: Student ID | B1: Name | C1: Topics taught | D1: Improvement Areas | E1: Achievements
A2: SS001 | B2: Fateh | C2: LCM GCF, Ecosystem, world map, Exponents, Nouns, Psuedo coding | E2: Good learner
A3: SS002 | B3: Amolpreet | C3: Letters A-E, number 1-10, counting number 1-10, simple addition technique on fingers | D3: word hard on learning letters and phonics | E3: Going slow in english but picking maths well
A4: SS003 | B4: Ravjodh | C4: Maths operations add, add with regrouping, subtract, 3 letter words, 4 letter s blends | D4: Lot of reading practice needed | E4: Good progress in class
A5: SS004 | B5: Alaina | C5: LCM GCF, Ecosystem, world map,Psuedo coding | D5: Need a lot of pratice in maths tables multiplication and division | E5: Good progress in class
A6: SS005 | B6: Kaya | C6: Maths operations add, add with regrouping, subtract, 3 letter words, 4 letter s blends | D6: More focus on words and spelling | E6: Picking maths operation at her own pace
A7: SS006 | B7: Gurshabd | C7: Letters A-z capital, small a-d. counting 1-10, simple addition technique on fingers | D7: Need to learn phonics | E7: Good at maths

Sheet Attendance Sep 2026
A1: ATTENDANCE — SEPTEMBER 2026
A2: Mark P = Present · A = Absent · blank if no class. Totals calculate automatically.
C3: T | D3: W | E3: T | F3: F | G3: S | H3: S | I3: M | J3: T | K3: W | L3: T | M3: F | N3: S | O3: S | P3: M | Q3: T | R3: W | S3: T | T3: F | U3: S | V3: S | W3: M | X3: T | Y3: W | Z3: T | AA3: F | AB3: S | AC3: S | AD3: M | AE3: T | AF3: W
A4: Student ID | B4: Name | C4: 1 | D4: 2 | E4: 3 | F4: 4 | G4: 5 | H4: 6 | I4: 7 | J4: 8 | K4: 9 | L4: 10 | M4: 11 | N4: 12 | O4: 13 | P4: 14 | Q4: 15 | R4: 16 | S4: 17 | T4: 18 | U4: 19 | V4: 20 | W4: 21 | X4: 22 | Y4: 23 | Z4: 24 | AA4: 25 | AB4: 26 | AC4: 27 | AD4: 28 | AE4: 29 | AF4: 30 | AG4: Total Classes Scheduled | AH4: Present | AI4: Absent | AJ4: Classes Held | AK4: Attendance %
A5: SS001 | B5: Fateh | C5: P | E5: P | I5: P | K5: P | L5: A | M5: P | P5: P | R5: P | S5: P | T5: P | W5: P | Y5: P | Z5: P | AG5: 13 | AH5: 12 | AI5: 1 | AJ5: 13 | AK5: 0.92307692
A6: SS002 | B6: Ravjodh | C6: P | E6: P | F6: P | I6: P | J6: P | L6: A | P6: P | Q6: P | S6: A | W6: P | X6: P | Z6: P | AG6: 12 | AH6: 10 | AI6: 2 | AJ6: 12 | AK6: 0.83333333
A7: SS003 | B7: Alaina | C7: P | E7: P | I7: P | K7: P | L7: A | M7: P | P7: P | R7: P | S7: P | T7: P | W7: P | Y7: P | Z7: P | AG7: 13 | AH7: 12 | AI7: 1 | AJ7: 13 | AK7: 0.92307692
A8: SS004 | B8: Kaya | E8: A | I8: P | L8: A | P8: P | S8: A | W8: P | Z8: P | AG8: 7 | AH8: 4 | AI8: 3 | AJ8: 7 | AK8: 0.57142857
A9: SS005 | B9: Gurshabd Singh Rawala | C9: P | E9: P | F9: P | I9: A | K9: P | M9: P | P9: P | R9: P | T9: P | W9: P | Y9: P | Z9: P | AG9: 12 | AH9: 11 | AI9: 1 | AJ9: 12 | AK9: 0.91666667
A10: SS006 | B10: Baani Purba | J10: P | L10: P | P10: P | Q10: P | S10: P | W10: P | X10: P | Z10: A | AG10: 8 | AH10: 7 | AI10: 1 | AJ10: 8 | AK10: 0.875
A11: SS007 | B11: Avneet Kaur Grewal | J11: P | L11: P | P11: P | Q11: P | S11: P | W11: P | X11: P | Z11: P | AG11: 8 | AH11: 8 | AI11: 0 | AJ11: 8 | AK11: 1
A12: SS008 | B12: Tanisha | H12: P | Q12: P | Y12: P | AG12: 3 | AH12: 3 | AI12: 0 | AJ12: 3 | AK12: 1
A13: SS009 | B13: Ekamjot | H13: P | Q13: P | Y13: P | AG13: 3 | AH13: 3 | AI13: 0 | AJ13: 3 | AK13: 1
A14: SS010 | B14: Viraj | H14: T | AG14: 0 | AH14: 0 | AI14: 0 | AJ14: 0

Sheet Fees Sep 2026
A1: FEES — SEPTEMBER 2026 (per class attended)
A2: Amount Due = classes held x per-class rate (absences still billed). Type Amount Paid; Balance & Status calculate.
A4: Student ID | B4: Name | C4: Grade | D4: Rate ($/class) | E4: Classes Held (billed) | F4: Class scheduled | G4: Amount Due ($) | H4: Amount Paid ($) | I4: Balance ($) | J4: Status | K4: Payment Date | L4: Method | M4: Notes
A5: SS001 | B5: Fateh | C5: Grade 7 | D5: 20 | E5: 13 | F5: 13 | G5: 260 | H5: 260 | I5: 0 | J5: Paid | M5: Batch1
A6: SS002 | B6: Ravjodh | C6: Grade 2 | D6: 15 | E6: 12 | F6: 12 | G6: 180 | H6: 180 | I6: 0 | J6: Paid | M6: Batch3
A7: SS003 | B7: Alaina | C7: Grade 7 | D7: 20 | E7: 13 | F7: 13 | G7: 260 | H7: 260 | I7: 0 | J7: Paid | M7: Batch1
A8: SS004 | B8: Kaya | C8: Grade 3 | D8: 15 | E8: 7 | F8: 7 | G8: 105 | H8: 110 | I8: -5 | J8: Paid | M8: Batch3
A9: SS005 | B9: Gurshabd Singh Rawala | C9: SK | D9: 10 | E9: 12 | F9: 12 | G9: 120 | H9: 120 | I9: 0 | J9: Paid | M9: Batch1
A10: SS006 | B10: Baani Purba | C10: Grade 3 | D10: 15 | E10: 8 | F10: 8 | G10: 120 | H10: 120 | I10: 0 | J10: Paid | M10: Batch3
A11: SS007 | B11: Avneet Kaur Grewal | C11: Grade 5 | D11: 20 | E11: 8 | F11: 8 | G11: 160 | H11: 160 | I11: 0 | J11: Paid | M11: Batch3
A12: SS008 | B12: Tanisha | C12: Coding | D12: 25 | E12: 3 | F12: 3 | G12: 75 | H12: 0 | I12: 75 | J12: Unpaid | M12: Batch4
A13: SS009 | B13: Ekamjot | C13: Coding | D13: 25 | E13: 3 | F13: 3 | G13: 75 | H13: 75 | I13: 0 | J13: Paid | M13: Batch4
A14: SS010 | B14: Viraj | C14: Coding | D14: 25 | E14: 0 | F14: 0 | G14: 0 | H14: 0 | I14: 0 | J14: — | M14: Batch4
B15: TOTAL | G15: 1355 | H15: 1265 | I15: 90

Sheet Report Sep 2026
A1: Student ID | B1: Name | C1: Topics taught | D1: Improvement Areas | E1: Achievements
A2: SS001 | B2: Fateh | C2: Food chain, food web, enerygy pyramid, carbon and water cycle, Decimals, exponents, power of tens, Nouns, plate techtonics, landforms,Squares and square roots, verbs, tenses (past) | E2: Good learner
A3: SS002 | B3: Ravjodh | C3: Addition of 2 digit numbers with word problems, subtraction of 2 digit number (no regrouping) with problems, 4 letter words r blends and l blends, nasal blends "mp". Animal classifications and characteristics, cursive writing a-o | D3: Focus more on reading level 1 books | E3: Good progress in class
A4: SS003 | B4: Alaina | C4: Food chain, food web, enerygy pyramid, carbon and water cycle, Decimals, exponents, power of tens, Nouns, plate techtonics, landforms,Squares and square roots, verbs, tenses (past) | D4: Need a lot of pratice in maths tables multiplication and division | E4: Good progress in class
A5: SS004 | B5: Kaya | C5: Addition of 2 digit numbers with word problems, subtraction of 2 digit number (no regrouping) with problems, 4 letter words r blends and l blends, reading comprehension, nasal blends "mp". | D5: Need writing practice | E5: Good progress in class. Try to attend all classes
A6: SS005 | B6: Gurshabd Singh Rawala | C6: small e-z, letter at and words with it. adding numbers 1-10 with simple addition technique on fingers,2 letter words at, in, on, 3 letter words with "AT" and associated 3 letter words. | D6: Need to learn phonics | E6: Good progress in class
A7: SS006 | B7: Baani Purba | C7: Addition of 2 digit number, word problems, round ups to tens, subtraction of 2 digit numbers, round ups to 100, reading comprehension, word problems on addition and subtraction, nasal blends "mp". | D7: Focus on communication more at home
A8: SS007 | B8: Avneet Kaur Grewal | C8: Round up to 10,000. Subtraction of 4 digit numbers, common noun vs proper nouns vs compound nouns, transitive and intransitive verbs, reading comprehension, multiplication 2 digit numbers,money addition subraction, matter, states of matter, properties of matter, units of matter | D8: Focus on communication more at home
A9: SS008 | B9: Tanisha
A10: SS009 | B10: Ekamjot

Sheet Attendance Oct 2026
A1: ATTENDANCE — OCTOBER 2026
A2: Mark P = Present · A = Absent · blank if no class. Totals calculate automatically.
C3: T | D3: F | E3: S | F3: S | G3: M | H3: T | I3: W | J3: T | K3: F | L3: S | M3: S | N3: M | O3: T | P3: W | Q3: T | R3: F | S3: S | T3: S | U3: M | V3: T | W3: W | X3: T | Y3: F | Z3: S | AA3: S | AB3: M | AC3: T | AD3: W | AE3: T | AF3: F | AG3: S
A4: Student ID | B4: Name | C4: 1 | D4: 2 | E4: 3 | F4: 4 | G4: 5 | H4: 6 | I4: 7 | J4: 8 | K4: 9 | L4: 10 | M4: 11 | N4: 12 | O4: 13 | P4: 14 | Q4: 15 | R4: 16 | S4: 17 | T4: 18 | U4: 19 | V4: 20 | W4: 21 | X4: 22 | Y4: 23 | Z4: 24 | AA4: 25 | AB4: 26 | AC4: 27 | AD4: 28 | AE4: 29 | AF4: 30 | AG4: 31 | AH4: Total classes scheuled | AI4: Present | AJ4: Absent | AK4: Classes Held | AL4: Attendance %
A5: SS001 | B5: {=IFERROR(INDEX(Students!$B$2:$B$106,MATCH($A5,Students!$A$2:$A$106,0)),"")} -> Fateh | C5: P | D5: P | G5: P | I5: S | K5: S | N5: S | P5: S | Q5: S | R5: S | U5: S | W5: S | X5: S | Y5: S | AB5: S | AE5: S | AF5: S | AH5: =COUNTA(C5:AG5) -> 16 | AI5: =COUNTIF(C5:AG5,"P") -> 3 | AJ5: =COUNTIF(C5:AG5,"A") -> 0 | AK5: =AI5+AJ5 -> 3 | AL5: =IFERROR(AI5/AK5,"") -> 1
A6: SS002 | B6: {=IFERROR(INDEX(Students!$B$2:$B$106,MATCH($A6,Students!$A$2:$A$106,0)),"")} -> Ravjodh | C6: P | G6: P | H6: P | J6: S | N6: S | O6: S | Q6: S | U6: S | V6: S | X6: S | AB6: S | AC6: S | AE6: S | AH6: =COUNTA(C6:AG6) -> 13 | AI6: =COUNTIF(C6:AG6,"P") -> 3 | AJ6: =COUNTIF(C6:AG6,"A") -> 0 | AK6: =AI6+AJ6 -> 3 | AL6: =IFERROR(AI6/AK6,"") -> 1
A7: SS003 | B7: {=IFERROR(INDEX(Students!$B$2:$B$106,MATCH($A7,Students!$A$2:$A$106,0)),"")} -> Alaina | C7: P | D7: P | G7: P | I7: S | K7: S | N7: S | P7: S | Q7: S | R7: S | U7: S | W7: S | X7: S | Y7: S | AB7: S | AE7: S | AF7: S | AH7: =COUNTA(C7:AG7) -> 16 | AI7: =COUNTIF(C7:AG7,"P") -> 3 | AJ7: =COUNTIF(C7:AG7,"A") -> 0 | AK7: =AI7+AJ7 -> 3 | AL7: =IFERROR(AI7/AK7,"") -> 1
A8: SS004 | B8: {=IFERROR(INDEX(Students!$B$2:$B$106,MATCH($A8,Students!$A$2:$A$106,0)),"")} -> Kaya | C8: A | J8: S | U8: S | X8: S | AB8: S | AE8: S | AH8: =COUNTA(C8:AG8) -> 6 | AI8: =COUNTIF(C8:AG8,"P") -> 0 | AJ8: =COUNTIF(C8:AG8,"A") -> 1 | AK8: =AI8+AJ8 -> 1 | AL8: =IFERROR(AI8/AK8,"") -> 0
A9: SS005 | B9: {=IFERROR(INDEX(Students!$B$2:$B$106,MATCH($A9,Students!$A$2:$A$106,0)),"")} -> Gurshabd Singh Rawala | C9: P | D9: P | G9: P | I9: S | K9: S | N9: S | P9: S | R9: S | U9: S | W9: S | Y9: S | AB9: S | AE9: S | AF9: S | AH9: =COUNTA(C9:AG9) -> 14 | AI9: =COUNTIF(C9:AG9,"P") -> 3 | AJ9: =COUNTIF(C9:AG9,"A") -> 0 | AK9: =AI9+AJ9 -> 3 | AL9: =IFERROR(AI9/AK9,"") -> 1
A10: SS006 | B10: {=IFERROR(INDEX(Students!$B$2:$B$106,MATCH($A10,Students!$A$2:$A$106,0)),"")} -> Baani Purba | C10: P | G10: P | H10: P | J10: S | N10: S | O10: S | Q10: S | U10: S | V10: S | X10: S | AB10: S | AC10: S | AE10: S | AH10: =COUNTA(C10:AG10) -> 13 | AI10: =COUNTIF(C10:AG10,"P") -> 3 | AJ10: =COUNTIF(C10:AG10,"A") -> 0 | AK10: =AI10+AJ10 -> 3 | AL10: =IFERROR(AI10/AK10,"") -> 1
A11: SS007 | B11: {=IFERROR(INDEX(Students!$B$2:$B$106,MATCH($A11,Students!$A$2:$A$106,0)),"")} -> Avneet Kaur Grewal | C11: P | G11: P | H11: P | J11: S | N11: S | O11: S | Q11: S | U11: S | V11: S | X11: S | AB11: S | AC11: S | AE11: S | AH11: =COUNTA(C11:AG11) -> 13 | AI11: =COUNTIF(C11:AG11,"P") -> 3 | AJ11: =COUNTIF(C11:AG11,"A") -> 0 | AK11: =AI11+AJ11 -> 3 | AL11: =IFERROR(AI11/AK11,"") -> 1
A12: SS008 | B12: {=IFERROR(INDEX(Students!$B$2:$B$106,MATCH($A12,Students!$A$2:$A$106,0)),"")} -> Tanisha | I12: S | P12: S | Y12: S | AF12: S | AH12: =COUNTA(C12:AG12) -> 4 | AI12: =COUNTIF(C12:AG12,"P") -> 0 | AJ12: =COUNTIF(C12:AG12,"A") -> 0 | AK12: =AI12+AJ12 -> 0 | AL12: =IFERROR(AI12/AK12,"")
A13: SS009 | B13: {=IFERROR(INDEX(Students!$B$2:$B$106,MATCH($A13,Students!$A$2:$A$106,0)),"")} -> xyz | U13: S | W13: S | Y13: S | AB13: S | AE13: S | AF13: S | AH13: =COUNTA(C13:AG13) -> 6 | AI13: =COUNTIF(C13:AG13,"P") -> 0 | AJ13: =COUNTIF(C13:AG13,"A") -> 0 | AK13: =AI13+AJ13 -> 0 | AL13: =IFERROR(AI13/AK13,"")
B14: {=IFERROR(INDEX(Students!$B$2:$B$106,MATCH($A14,Students!$A$2:$A$106,0)),"")}

Sheet Fees Oct 2026
A1: FEES — OCTOBER 2026 (per class attended)
A2: Amount Due = classes held x per-class rate (absences still billed). Type Amount Paid; Balance & Status calculate.
A4: Student ID | B4: Name | C4: Grade | D4: Rate ($/class) | E4: Classes Held (billed) | F4: Classes scheduled | G4: Amount Due ($) | H4: Amount Paid ($) | I4: Balance ($) | J4: Status | K4: Payment Date | L4: Method | M4: Notes
A5: SS001 | B5: {=IFERROR(INDEX(Students!$B$2:$B$106,MATCH($A5,Students!$A$2:$A$106,0)),"")} -> Fateh | C5: {=IFERROR(INDEX(Students!$D$2:$D$106,MATCH($A5,Students!$A$2:$A$106,0)),"")} -> Grade 7 | D5: {=IFERROR(INDEX(Students!$O$2:$O$106,MATCH($A5,Students!$A$2:$A$106,0)),0)} -> 20 | E5: {=IFERROR(INDEX('Attendance Oct 2026'!$AK$5:$AK$98,MATCH($A5,'Attendance Oct 2026'!$A$5:$A$98,0)),0)} -> 3 | F5: =vlookup(A5,'Attendance Oct 2026'!A:AH,34,0) -> 16 | G5: =D5*F5 -> 320 | H5: 0 | I5: =G5-H5 -> 320 | J5: =IF(G5=0,"—",IF(H5>=G5,"Paid",IF(H5=0,"Unpaid","Partial"))) -> Unpaid
A6: SS002 | B6: {=IFERROR(INDEX(Students!$B$2:$B$106,MATCH($A6,Students!$A$2:$A$106,0)),"")} -> Ravjodh | C6: {=IFERROR(INDEX(Students!$D$2:$D$106,MATCH($A6,Students!$A$2:$A$106,0)),"")} -> Grade 2 | D6: {=IFERROR(INDEX(Students!$O$2:$O$106,MATCH($A6,Students!$A$2:$A$106,0)),0)} -> 15 | E6: {=IFERROR(INDEX('Attendance Oct 2026'!$AK$5:$AK$98,MATCH($A6,'Attendance Oct 2026'!$A$5:$A$98,0)),0)} -> 3 | F6: =vlookup(A6,'Attendance Oct 2026'!A:AH,34,0) -> 13 | G6: =D6*F6 -> 195 | H6: 80 | I6: =G6-H6 -> 115 | J6: =IF(G6=0,"—",IF(H6>=G6,"Paid",IF(H6=0,"Unpaid","Partial"))) -> Partial | K6: 46300 | L6: Cash | M6: Parially paid
A7: SS003 | B7: {=IFERROR(INDEX(Students!$B$2:$B$106,MATCH($A7,Students!$A$2:$A$106,0)),"")} -> Alaina | C7: {=IFERROR(INDEX(Students!$D$2:$D$106,MATCH($A7,Students!$A$2:$A$106,0)),"")} -> Grade 7 | D7: {=IFERROR(INDEX(Students!$O$2:$O$106,MATCH($A7,Students!$A$2:$A$106,0)),0)} -> 20 | E7: {=IFERROR(INDEX('Attendance Oct 2026'!$AK$5:$AK$98,MATCH($A7,'Attendance Oct 2026'!$A$5:$A$98,0)),0)} -> 3 | F7: =vlookup(A7,'Attendance Oct 2026'!A:AH,34,0) -> 16 | G7: =D7*F7 -> 320 | H7: 0 | I7: =G7-H7 -> 320 | J7: =IF(G7=0,"—",IF(H7>=G7,"Paid",IF(H7=0,"Unpaid","Partial"))) -> Unpaid
A8: SS004 | B8: {=IFERROR(INDEX(Students!$B$2:$B$106,MATCH($A8,Students!$A$2:$A$106,0)),"")} -> Kaya | C8: {=IFERROR(INDEX(Students!$D$2:$D$106,MATCH($A8,Students!$A$2:$A$106,0)),"")} -> Grade 3 | D8: {=IFERROR(INDEX(Students!$O$2:$O$106,MATCH($A8,Students!$A$2:$A$106,0)),0)} -> 15 | E8: {=IFERROR(INDEX('Attendance Oct 2026'!$AK$5:$AK$98,MATCH($A8,'Attendance Oct 2026'!$A$5:$A$98,0)),0)} -> 1 | F8: =vlookup(A8,'Attendance Oct 2026'!A:AH,34,0) -> 6 | G8: =D8*F8 -> 90 | H8: 5 | I8: =G8-H8 -> 85 | J8: =IF(G8=0,"—",IF(H8>=G8,"Paid",IF(H8=0,"Unpaid","Partial"))) -> Partial
A9: SS005 | B9: {=IFERROR(INDEX(Students!$B$2:$B$106,MATCH($A9,Students!$A$2:$A$106,0)),"")} -> Gurshabd Singh Rawala | C9: {=IFERROR(INDEX(Students!$D$2:$D$106,MATCH($A9,Students!$A$2:$A$106,0)),"")} -> SK | D9: {=IFERROR(INDEX(Students!$O$2:$O$106,MATCH($A9,Students!$A$2:$A$106,0)),0)} -> 10 | E9: {=IFERROR(INDEX('Attendance Oct 2026'!$AK$5:$AK$98,MATCH($A9,'Attendance Oct 2026'!$A$5:$A$98,0)),0)} -> 3 | F9: =vlookup(A9,'Attendance Oct 2026'!A:AH,34,0) -> 14 | G9: =D9*F9 -> 140 | H9: 0 | I9: =G9-H9 -> 140 | J9: =IF(G9=0,"—",IF(H9>=G9,"Paid",IF(H9=0,"Unpaid","Partial"))) -> Unpaid
A10: SS006 | B10: {=IFERROR(INDEX(Students!$B$2:$B$106,MATCH($A10,Students!$A$2:$A$106,0)),"")} -> Baani Purba | C10: {=IFERROR(INDEX(Students!$D$2:$D$106,MATCH($A10,Students!$A$2:$A$106,0)),"")} -> Grade 3 | D10: {=IFERROR(INDEX(Students!$O$2:$O$106,MATCH($A10,Students!$A$2:$A$106,0)),0)} -> 15 | E10: {=IFERROR(INDEX('Attendance Oct 2026'!$AK$5:$AK$98,MATCH($A10,'Attendance Oct 2026'!$A$5:$A$98,0)),0)} -> 3 | F10: =vlookup(A10,'Attendance Oct 2026'!A:AH,34,0) -> 13 | G10: =D10*F10 -> 195 | H10: 195 | I10: =G10-H10 -> 0 | J10: =IF(G10=0,"—",IF(H10>=G10,"Paid",IF(H10=0,"Unpaid","Partial"))) -> Paid | K10: 46301 | L10: Cash
A11: SS007 | B11: {=IFERROR(INDEX(Students!$B$2:$B$106,MATCH($A11,Students!$A$2:$A$106,0)),"")} -> Avneet Kaur Grewal | C11: {=IFERROR(INDEX(Students!$D$2:$D$106,MATCH($A11,Students!$A$2:$A$106,0)),"")} -> Grade 5 | D11: {=IFERROR(INDEX(Students!$O$2:$O$106,MATCH($A11,Students!$A$2:$A$106,0)),0)} -> 20 | E11: {=IFERROR(INDEX('Attendance Oct 2026'!$AK$5:$AK$98,MATCH($A11,'Attendance Oct 2026'!$A$5:$A$98,0)),0)} -> 3 | F11: =vlookup(A11,'Attendance Oct 2026'!A:AH,34,0) -> 13 | G11: =D11*F11 -> 260 | H11: 260 | I11: =G11-H11 -> 0 | J11: =IF(G11=0,"—",IF(H11>=G11,"Paid",IF(H11=0,"Unpaid","Partial"))) -> Paid | K11: 46301 | L11: Cash
A12: SS008 | B12: {=IFERROR(INDEX(Students!$B$2:$B$106,MATCH($A12,Students!$A$2:$A$106,0)),"")} -> Tanisha | C12: {=IFERROR(INDEX(Students!$D$2:$D$106,MATCH($A12,Students!$A$2:$A$106,0)),"")} -> Coding | D12: {=IFERROR(INDEX(Students!$O$2:$O$106,MATCH($A12,Students!$A$2:$A$106,0)),0)} -> 25 | E12: {=IFERROR(INDEX('Attendance Oct 2026'!$AK$5:$AK$98,MATCH($A12,'Attendance Oct 2026'!$A$5:$A$98,0)),0)} -> 0 | F12: =vlookup(A12,'Attendance Oct 2026'!A:AH,34,0) -> 4 | G12: =D12*F12 -> 100 | H12: 0 | I12: =G12-H12 -> 100 | J12: =IF(G12=0,"—",IF(H12>=G12,"Paid",IF(H12=0,"Unpaid","Partial"))) -> Unpaid
A13: SS009 | B13: {=IFERROR(INDEX(Students!$B$2:$B$106,MATCH($A13,Students!$A$2:$A$106,0)),"")} -> xyz | C13: {=IFERROR(INDEX(Students!$D$2:$D$106,MATCH($A13,Students!$A$2:$A$106,0)),"")} -> Grade 2 | D13: {=IFERROR(INDEX(Students!$O$2:$O$106,MATCH($A13,Students!$A$2:$A$106,0)),0)} -> 15 | E13: {=IFERROR(INDEX('Attendance Oct 2026'!$AK$5:$AK$98,MATCH($A13,'Attendance Oct 2026'!$A$5:$A$98,0)),0)} -> 0 | F13: =vlookup(A13,'Attendance Oct 2026'!A:AH,34,0) -> 6 | G13: =D13*F13 -> 90 | H13: 0 | I13: =G13-H13 -> 90 | J13: =IF(G13=0,"—",IF(H13>=G13,"Paid",IF(H13=0,"Unpaid","Partial"))) -> Unpaid
B14: TOTAL | G14: =SUM(G5:G13) -> 1710 | H14: =SUM(H5:H13) -> 540 | I14: =SUM(I5:I13) -> 1170

Sheet Report Oct 2026
A1: Student ID | B1: Name | C1: Topics taught | D1: Improvement Areas | E1: Achievements
A2: SS001 | B2: Fateh | C2: Patterns, Multiplication and Division | E2: Good learner
A3: SS002 | B3: Ravjodh | C3: BL cl words reading comprehension, "at" "an" "ap" "ad" "am" "ag" words along with short stories | E3: Good progress in class
A4: SS003 | B4: Alaina | C4: Patterns, Multiplication and Division | E4: Good progress in class
A5: SS004 | B5: Kaya | E5: Good progress in class. Try to attend all classes
A6: SS005 | B6: Gurshabd Singh Rawala | C6: AT, IN words | E6: Good progress in class
A7: SS006 | B7: Baani Purba | C7: BL cl words reading comprehension, 2 digit addition
A8: SS007 | B8: Avneet Kaur Grewal | C8: Cells, Decimals, 3 digit division worksheet
A9: SS008 | B9: Tanisha
A10: SS009 | B10: Ekamjot

Sheet Attendance Nov 2026
A1: ATTENDANCE — NOVEMBER 2026
A2: Mark P = Present · A = Absent · blank if no class. Totals calculate automatically.
C3: S | D3: M | E3: T | F3: W | G3: T | H3: F | I3: S | J3: S | K3: M | L3: T | M3: W | N3: T | O3: F | P3: S | Q3: S | R3: M | S3: T | T3: W | U3: T | V3: F | W3: S | X3: S | Y3: M | Z3: T | AA3: W | AB3: T | AC3: F | AD3: S | AE3: S | AF3: M
A4: Student ID | B4: Name | C4: 1 | D4: 2 | E4: 3 | F4: 4 | G4: 5 | H4: 6 | I4: 7 | J4: 8 | K4: 9 | L4: 10 | M4: 11 | N4: 12 | O4: 13 | P4: 14 | Q4: 15 | R4: 16 | S4: 17 | T4: 18 | U4: 19 | V4: 20 | W4: 21 | X4: 22 | Y4: 23 | Z4: 24 | AA4: 25 | AB4: 26 | AC4: 27 | AD4: 28 | AE4: 29 | AF4: 30 | AG4: Present | AH4: Absent | AI4: Classes Held | AJ4: Attendance %
A5: SS001 | B5: {=IFERROR(INDEX(Students!$B$2:$B$106,MATCH($A5,Students!$A$2:$A$106,0)),"")} -> Fateh | AG5: =COUNTIF(C5:AF5,"P") -> 0 | AH5: =COUNTIF(C5:AF5,"A") -> 0 | AI5: =AG5+AH5 -> 0 | AJ5: =IFERROR(AG5/AI5,"")
A6: SS002 | B6: {=IFERROR(INDEX(Students!$B$2:$B$106,MATCH($A6,Students!$A$2:$A$106,0)),"")} -> Ravjodh | AG6: =COUNTIF(C6:AF6,"P") -> 0 | AH6: =COUNTIF(C6:AF6,"A") -> 0 | AI6: =AG6+AH6 -> 0 | AJ6: =IFERROR(AG6/AI6,"")
A7: SS003 | B7: {=IFERROR(INDEX(Students!$B$2:$B$106,MATCH($A7,Students!$A$2:$A$106,0)),"")} -> Alaina | AG7: =COUNTIF(C7:AF7,"P") -> 0 | AH7: =COUNTIF(C7:AF7,"A") -> 0 | AI7: =AG7+AH7 -> 0 | AJ7: =IFERROR(AG7/AI7,"")
A8: SS004 | B8: {=IFERROR(INDEX(Students!$B$2:$B$106,MATCH($A8,Students!$A$2:$A$106,0)),"")} -> Kaya | AG8: =COUNTIF(C8:AF8,"P") -> 0 | AH8: =COUNTIF(C8:AF8,"A") -> 0 | AI8: =AG8+AH8 -> 0 | AJ8: =IFERROR(AG8/AI8,"")
A9: SS005 | B9: {=IFERROR(INDEX(Students!$B$2:$B$106,MATCH($A9,Students!$A$2:$A$106,0)),"")} -> Gurshabd Singh Rawala | AG9: =COUNTIF(C9:AF9,"P") -> 0 | AH9: =COUNTIF(C9:AF9,"A") -> 0 | AI9: =AG9+AH9 -> 0 | AJ9: =IFERROR(AG9/AI9,"")
A10: SS006 | B10: {=IFERROR(INDEX(Students!$B$2:$B$106,MATCH($A10,Students!$A$2:$A$106,0)),"")} -> Baani Purba | AG10: =COUNTIF(C10:AF10,"P") -> 0 | AH10: =COUNTIF(C10:AF10,"A") -> 0 | AI10: =AG10+AH10 -> 0 | AJ10: =IFERROR(AG10/AI10,"")
A11: SS007 | B11: {=IFERROR(INDEX(Students!$B$2:$B$106,MATCH($A11,Students!$A$2:$A$106,0)),"")} -> Avneet Kaur Grewal | AG11: =COUNTIF(C11:AF11,"P") -> 0 | AH11: =COUNTIF(C11:AF11,"A") -> 0 | AI11: =AG11+AH11 -> 0 | AJ11: =IFERROR(AG11/AI11,"")
A12: SS008 | B12: {=IFERROR(INDEX(Students!$B$2:$B$106,MATCH($A12,Students!$A$2:$A$106,0)),"")} -> Tanisha | AG12: =COUNTIF(C12:AF12,"P") -> 0 | AH12: =COUNTIF(C12:AF12,"A") -> 0 | AI12: =AG12+AH12 -> 0 | AJ12: =IFERROR(AG12/AI12,"")
A13: SS009 | B13: {=IFERROR(INDEX(Students!$B$2:$B$106,MATCH($A13,Students!$A$2:$A$106,0)),"")} -> xyz | AG13: =COUNTIF(C13:AF13,"P") -> 0 | AH13: =COUNTIF(C13:AF13,"A") -> 0 | AI13: =AG13+AH13 -> 0 | AJ13: =IFERROR(AG13/AI13,"")

Sheet Fees Nov 2026
A1: FEES — NOVEMBER 2026 (per class attended)
A2: Amount Due = classes held x per-class rate (absences still billed). Type Amount Paid; Balance & Status calculate.
A4: Student ID | B4: Name | C4: Grade | D4: Rate ($/class) | E4: Classes Held (billed) | F4: Amount Due ($) | G4: Amount Paid ($) | H4: Balance ($) | I4: Status | J4: Payment Date | K4: Method | L4: Notes
A5: SS001 | B5: {=IFERROR(INDEX(Students!$B$2:$B$106,MATCH($A5,Students!$A$2:$A$106,0)),"")} -> Fateh | C5: {=IFERROR(INDEX(Students!$D$2:$D$106,MATCH($A5,Students!$A$2:$A$106,0)),"")} -> Grade 7 | D5: {=IFERROR(INDEX(Students!$O$2:$O$106,MATCH($A5,Students!$A$2:$A$106,0)),0)} -> 20 | E5: {=IFERROR(INDEX('Attendance Nov 2026'!$AI$5:$AI$100,MATCH($A5,'Attendance Nov 2026'!$A$5:$A$100,0)),0)} -> 0 | F5: =IFERROR(D5*E5,0) -> 0 | G5: 0 | H5: =F5-G5 -> 0 | I5: =IF(F5=0,"—",IF(G5>=F5,"Paid",IF(G5=0,"Unpaid","Partial"))) -> —
A6: SS002 | B6: {=IFERROR(INDEX(Students!$B$2:$B$106,MATCH($A6,Students!$A$2:$A$106,0)),"")} -> Ravjodh | C6: {=IFERROR(INDEX(Students!$D$2:$D$106,MATCH($A6,Students!$A$2:$A$106,0)),"")} -> Grade 2 | D6: {=IFERROR(INDEX(Students!$O$2:$O$106,MATCH($A6,Students!$A$2:$A$106,0)),0)} -> 15 | E6: {=IFERROR(INDEX('Attendance Nov 2026'!$AI$5:$AI$100,MATCH($A6,'Attendance Nov 2026'!$A$5:$A$100,0)),0)} -> 0 | F6: =IFERROR(D6*E6,0) -> 0 | G6: 0 | H6: =F6-G6 -> 0 | I6: =IF(F6=0,"—",IF(G6>=F6,"Paid",IF(G6=0,"Unpaid","Partial"))) -> —
A7: SS003 | B7: {=IFERROR(INDEX(Students!$B$2:$B$106,MATCH($A7,Students!$A$2:$A$106,0)),"")} -> Alaina | C7: {=IFERROR(INDEX(Students!$D$2:$D$106,MATCH($A7,Students!$A$2:$A$106,0)),"")} -> Grade 7 | D7: {=IFERROR(INDEX(Students!$O$2:$O$106,MATCH($A7,Students!$A$2:$A$106,0)),0)} -> 20 | E7: {=IFERROR(INDEX('Attendance Nov 2026'!$AI$5:$AI$100,MATCH($A7,'Attendance Nov 2026'!$A$5:$A$100,0)),0)} -> 0 | F7: =IFERROR(D7*E7,0) -> 0 | G7: 0 | H7: =F7-G7 -> 0 | I7: =IF(F7=0,"—",IF(G7>=F7,"Paid",IF(G7=0,"Unpaid","Partial"))) -> —
A8: SS004 | B8: {=IFERROR(INDEX(Students!$B$2:$B$106,MATCH($A8,Students!$A$2:$A$106,0)),"")} -> Kaya | C8: {=IFERROR(INDEX(Students!$D$2:$D$106,MATCH($A8,Students!$A$2:$A$106,0)),"")} -> Grade 3 | D8: {=IFERROR(INDEX(Students!$O$2:$O$106,MATCH($A8,Students!$A$2:$A$106,0)),0)} -> 15 | E8: {=IFERROR(INDEX('Attendance Nov 2026'!$AI$5:$AI$100,MATCH($A8,'Attendance Nov 2026'!$A$5:$A$100,0)),0)} -> 0 | F8: =IFERROR(D8*E8,0) -> 0 | G8: 0 | H8: =F8-G8 -> 0 | I8: =IF(F8=0,"—",IF(G8>=F8,"Paid",IF(G8=0,"Unpaid","Partial"))) -> —
B9: TOTAL | F9: =SUM(F5:F8) -> 0 | G9: =SUM(G5:G8) -> 0 | H9: =SUM(H5:H8) -> 0

Sheet Attendance Dec 2026
A1: ATTENDANCE — DECEMBER 2026
A2: Mark P = Present · A = Absent · blank if no class. Totals calculate automatically.
C3: T | D3: W | E3: T | F3: F | G3: S | H3: S | I3: M | J3: T | K3: W | L3: T | M3: F | N3: S | O3: S | P3: M | Q3: T | R3: W | S3: T | T3: F | U3: S | V3: S | W3: M | X3: T | Y3: W | Z3: T | AA3: F | AB3: S | AC3: S | AD3: M | AE3: T | AF3: W | AG3: T
A4: Student ID | B4: Name | C4: 1 | D4: 2 | E4: 3 | F4: 4 | G4: 5 | H4: 6 | I4: 7 | J4: 8 | K4: 9 | L4: 10 | M4: 11 | N4: 12 | O4: 13 | P4: 14 | Q4: 15 | R4: 16 | S4: 17 | T4: 18 | U4: 19 | V4: 20 | W4: 21 | X4: 22 | Y4: 23 | Z4: 24 | AA4: 25 | AB4: 26 | AC4: 27 | AD4: 28 | AE4: 29 | AF4: 30 | AG4: 31 | AH4: Present | AI4: Absent | AJ4: Classes Held | AK4: Attendance %
A5: SS001 | B5: {=IFERROR(INDEX(Students!$B$2:$B$106,MATCH($A5,Students!$A$2:$A$106,0)),"")} -> Fateh | AH5: =COUNTIF(C5:AG5,"P") -> 0 | AI5: =COUNTIF(C5:AG5,"A") -> 0 | AJ5: =AH5+AI5 -> 0 | AK5: =IFERROR(AH5/AJ5,"")
A6: SS002 | B6: {=IFERROR(INDEX(Students!$B$2:$B$106,MATCH($A6,Students!$A$2:$A$106,0)),"")} -> Ravjodh | AH6: =COUNTIF(C6:AG6,"P") -> 0 | AI6: =COUNTIF(C6:AG6,"A") -> 0 | AJ6: =AH6+AI6 -> 0 | AK6: =IFERROR(AH6/AJ6,"")
A7: SS003 | B7: {=IFERROR(INDEX(Students!$B$2:$B$106,MATCH($A7,Students!$A$2:$A$106,0)),"")} -> Alaina | AH7: =COUNTIF(C7:AG7,"P") -> 0 | AI7: =COUNTIF(C7:AG7,"A") -> 0 | AJ7: =AH7+AI7 -> 0 | AK7: =IFERROR(AH7/AJ7,"")
A8: SS004 | B8: {=IFERROR(INDEX(Students!$B$2:$B$106,MATCH($A8,Students!$A$2:$A$106,0)),"")} -> Kaya | AH8: =COUNTIF(C8:AG8,"P") -> 0 | AI8: =COUNTIF(C8:AG8,"A") -> 0 | AJ8: =AH8+AI8 -> 0 | AK8: =IFERROR(AH8/AJ8,"")

Sheet Fees Dec 2026
A1: FEES — DECEMBER 2026 (per class attended)
A2: Amount Due = classes held x per-class rate (absences still billed). Type Amount Paid; Balance & Status calculate.
A4: Student ID | B4: Name | C4: Grade | D4: Rate ($/class) | E4: Classes Held (billed) | F4: Amount Due ($) | G4: Amount Paid ($) | H4: Balance ($) | I4: Status | J4: Payment Date | K4: Method | L4: Notes
A5: SS001 | B5: {=IFERROR(INDEX(Students!$B$2:$B$106,MATCH($A5,Students!$A$2:$A$106,0)),"")} -> Fateh | C5: {=IFERROR(INDEX(Students!$D$2:$D$106,MATCH($A5,Students!$A$2:$A$106,0)),"")} -> Grade 7 | D5: {=IFERROR(INDEX(Students!$O$2:$O$106,MATCH($A5,Students!$A$2:$A$106,0)),0)} -> 20 | E5: {=IFERROR(INDEX('Attendance Dec 2026'!$AJ$5:$AJ$100,MATCH($A5,'Attendance Dec 2026'!$A$5:$A$100,0)),0)} -> 0 | F5: =IFERROR(D5*E5,0) -> 0 | G5: 0 | H5: =F5-G5 -> 0 | I5: =IF(F5=0,"—",IF(G5>=F5,"Paid",IF(G5=0,"Unpaid","Partial"))) -> —
A6: SS002 | B6: {=IFERROR(INDEX(Students!$B$2:$B$106,MATCH($A6,Students!$A$2:$A$106,0)),"")} -> Ravjodh | C6: {=IFERROR(INDEX(Students!$D$2:$D$106,MATCH($A6,Students!$A$2:$A$106,0)),"")} -> Grade 2 | D6: {=IFERROR(INDEX(Students!$O$2:$O$106,MATCH($A6,Students!$A$2:$A$106,0)),0)} -> 15 | E6: {=IFERROR(INDEX('Attendance Dec 2026'!$AJ$5:$AJ$100,MATCH($A6,'Attendance Dec 2026'!$A$5:$A$100,0)),0)} -> 0 | F6: =IFERROR(D6*E6,0) -> 0 | G6: 0 | H6: =F6-G6 -> 0 | I6: =IF(F6=0,"—",IF(G6>=F6,"Paid",IF(G6=0,"Unpaid","Partial"))) -> —
A7: SS003 | B7: {=IFERROR(INDEX(Students!$B$2:$B$106,MATCH($A7,Students!$A$2:$A$106,0)),"")} -> Alaina | C7: {=IFERROR(INDEX(Students!$D$2:$D$106,MATCH($A7,Students!$A$2:$A$106,0)),"")} -> Grade 7 | D7: {=IFERROR(INDEX(Students!$O$2:$O$106,MATCH($A7,Students!$A$2:$A$106,0)),0)} -> 20 | E7: {=IFERROR(INDEX('Attendance Dec 2026'!$AJ$5:$AJ$100,MATCH($A7,'Attendance Dec 2026'!$A$5:$A$100,0)),0)} -> 0 | F7: =IFERROR(D7*E7,0) -> 0 | G7: 0 | H7: =F7-G7 -> 0 | I7: =IF(F7=0,"—",IF(G7>=F7,"Paid",IF(G7=0,"Unpaid","Partial"))) -> —
A8: SS004 | B8: {=IFERROR(INDEX(Students!$B$2:$B$106,MATCH($A8,Students!$A$2:$A$106,0)),"")} -> Kaya | C8: {=IFERROR(INDEX(Students!$D$2:$D$106,MATCH($A8,Students!$A$2:$A$106,0)),"")} -> Grade 3 | D8: {=IFERROR(INDEX(Students!$O$2:$O$106,MATCH($A8,Students!$A$2:$A$106,0)),0)} -> 15 | E8: {=IFERROR(INDEX('Attendance Dec 2026'!$AJ$5:$AJ$100,MATCH($A8,'Attendance Dec 2026'!$A$5:$A$100,0)),0)} -> 0 | F8: =IFERROR(D8*E8,0) -> 0 | G8: 0 | H8: =F8-G8 -> 0 | I8: =IF(F8=0,"—",IF(G8>=F8,"Paid",IF(G8=0,"Unpaid","Partial"))) -> —
B9: TOTAL | F9: =SUM(F5:F8) -> 0 | G9: =SUM(G5:G8) -> 0 | H9: =SUM(H5:H8) -> 0

Sheet Payments Log
A1: Date | B1: Receipt # | C1: Student ID | D1: Name | E1: Month | F1: Amount ($) | G1: Method | H1: Recorded By | I1: Notes
A2: 2026-08-05 | B2: R-1001 | C2: SS001 | D2: {=IFERROR(INDEX(Students!$B$2:$B$106,MATCH($C2,Students!$A$2:$A$106,0)),"")} -> Fateh | E2: Aug 2026 | F2: 60 | G2: e-Transfer | H2: (Example) | I2: ← EXAMPLE — delete or overwrite
D3: {=IFERROR(INDEX(Students!$B$2:$B$106,MATCH($C3,Students!$A$2:$A$106,0)),"")}
D4: {=IFERROR(INDEX(Students!$B$2:$B$106,MATCH($C4,Students!$A$2:$A$106,0)),"")}
D5: {=IFERROR(INDEX(Students!$B$2:$B$106,MATCH($C5,Students!$A$2:$A$106,0)),"")}
D6: {=IFERROR(INDEX(Students!$B$2:$B$106,MATCH($C6,Students!$A$2:$A$106,0)),"")}
D7: {=IFERROR(INDEX(Students!$B$2:$B$106,MATCH($C7,Students!$A$2:$A$106,0)),"")}
D8: {=IFERROR(INDEX(Students!$B$2:$B$106,MATCH($C8,Students!$A$2:$A$106,0)),"")}
D9: {=IFERROR(INDEX(Students!$B$2:$B$106,MATCH($C9,Students!$A$2:$A$106,0)),"")}
D10: {=IFERROR(INDEX(Students!$B$2:$B$106,MATCH($C10,Students!$A$2:$A$106,0)),"")}
D11: {=IFERROR(INDEX(Students!$B$2:$B$106,MATCH($C11,Students!$A$2:$A$106,0)),"")}
D12: {=IFERROR(INDEX(Students!$B$2:$B$106,MATCH($C12,Students!$A$2:$A$106,0)),"")}
D13: {=IFERROR(INDEX(Students!$B$2:$B$106,MATCH($C13,Students!$A$2:$A$106,0)),"")}
D14: {=IFERROR(INDEX(Students!$B$2:$B$106,MATCH($C14,Students!$A$2:$A$106,0)),"")}
... D40: {=IFERROR(INDEX(Students!$B$2:$B$106,MATCH($C40,Students!$A$2:$A$106,0)),"")}

Sheet Dashboard
B2: DASHBOARD
B3: Live totals — updates as you fill the other sheets.
B5: STUDENTS
B6: Active students | C6: =COUNTIF(Students!P2:P106,"Active") -> 8
B7: Inactive students | C7: =COUNTIF(Students!P2:P106,"Inactive") -> 7
B9: FEES — AUGUST 2026
B10: Fees billed (due) | C10: ='Fees Aug 2026'!G11 -> 930
B11: Fees collected | C11: ='Fees Aug 2026'!H11 -> 960
B12: Outstanding balance | C12: ='Fees Aug 2026'!I11 -> -30
B13: Collection rate | C13: =IFERROR('Fees Aug 2026'!H11/'Fees Aug 2026'!G11,0) -> 1.0322581
B15: ATTENDANCE — AUGUST 2026
B16: Classes held (max) | C16: =MAX('Attendance Aug 2026'!AK5:AK8) -> 16
B17: Average attendance | C17: =IFERROR(AVERAGE('Attendance Aug 2026'!AL5:AL8),"") -> 0.90945513
B19: MONTHLY SUMMARY — 2026
B20: Month | C20: Billed ($) | D20: Collected ($) | E20: Outstanding ($)
B21: Aug 2026 | C21: ='Fees Aug 2026'!G11 -> 930 | D21: ='Fees Aug 2026'!H11 -> 960 | E21: ='Fees Aug 2026'!I11 -> -30
B22: Sep 2026 | C22: ='Fees Sep 2026'!G15 -> 1355 | D22: ='Fees Sep 2026'!H15 -> 1265 | E22: ='Fees Sep 2026'!I15 -> 90
B23: Oct 2026 | C23: ='Fees Oct 2026'!G14 -> 1710 | D23: ='Fees Oct 2026'!H14 -> 540 | E23: ='Fees Oct 2026'!I14 -> 1170
B24: Nov 2026 | C24: ='Fees Nov 2026'!F9 -> 0 | D24: ='Fees Nov 2026'!G9 -> 0 | E24: ='Fees Nov 2026'!H9 -> 0
B25: Dec 2026 | C25: ='Fees Dec 2026'!F9 -> 0 | D25: ='Fees Dec 2026'!G9 -> 0 | E25: ='Fees Dec 2026'!H9 -> 0
B26: YEAR TOTAL | C26: =SUM(C21:C25) -> 3995 | D26: =SUM(D21:D25) -> 2765 | E26: =SUM(E21:E25) -> 1230
